jupyterhub_url_sharing/.gitignore
jupyterhub_url_sharing/.prettierignore
jupyterhub_url_sharing/__init__.py
jupyterhub_url_sharing/_version.py
jupyterhub_url_sharing/labextension/package.json
jupyterhub_url_sharing/labextension/static/568.28a4cef7f33ca1e0f636.js
jupyterhub_url_sharing/labextension/static/747.9dbdef79181d512ff2a1.js
jupyterhub_url_sharing/labextension/static/remoteEntry.c21229788728e42d4937.js
jupyterhub_url_sharing/labextension/static/style.js
jupyterhub_url_sharing/labextension/static/third-party-licenses.json
jupyterhub_url_sharing-0.1.0.data/data/share/jupyter/labextensions/jupyterhub-url-sharing/package.json
jupyterhub_url_sharing-0.1.0.data/data/share/jupyter/labextensions/jupyterhub-url-sharing/static/568.28a4cef7f33ca1e0f636.js
jupyterhub_url_sharing-0.1.0.data/data/share/jupyter/labextensions/jupyterhub-url-sharing/static/747.9dbdef79181d512ff2a1.js
jupyterhub_url_sharing-0.1.0.data/data/share/jupyter/labextensions/jupyterhub-url-sharing/static/remoteEntry.c21229788728e42d4937.js
jupyterhub_url_sharing-0.1.0.data/data/share/jupyter/labextensions/jupyterhub-url-sharing/static/style.js
jupyterhub_url_sharing-0.1.0.data/data/share/jupyter/labextensions/jupyterhub-url-sharing/static/third-party-licenses.json
jupyterhub_url_sharing-0.1.0.data/data/share/jupyter/labextensions/jupyterhub-url-sharing/install.json
jupyterhub_url_sharing-0.1.0.dist-info/METADATA
jupyterhub_url_sharing-0.1.0.dist-info/WHEEL
jupyterhub_url_sharing-0.1.0.dist-info/licenses/LICENSE
jupyterhub_url_sharing-0.1.0.dist-info/RECORD
